.gitignore
LICENSE
README.md
pylintrc
setup.py
tox.ini
.github/workflows/tests.yml
.vscode/launch.json
docs/Makefile
docs/conf.py
docs/index.rst
docs/make.bat
docs/pyhpecw7.comware.rst
docs/pyhpecw7.errors.rst
docs/pyhpecw7.execkeys.rst
docs/pyhpecw7.features.cleanerase.rst
docs/pyhpecw7.features.config.rst
docs/pyhpecw7.features.errors.rst
docs/pyhpecw7.features.facts.rst
docs/pyhpecw7.features.file_copy.rst
docs/pyhpecw7.features.install_os.rst
docs/pyhpecw7.features.interface.rst
docs/pyhpecw7.features.ipinterface.rst
docs/pyhpecw7.features.irf.rst
docs/pyhpecw7.features.l2vpn.rst
docs/pyhpecw7.features.neighbor.rst
docs/pyhpecw7.features.ping.rst
docs/pyhpecw7.features.portchannel.rst
docs/pyhpecw7.features.reboot.rst
docs/pyhpecw7.features.rst
docs/pyhpecw7.features.switchport.rst
docs/pyhpecw7.features.vlan.rst
docs/pyhpecw7.features.vrrp.rst
docs/pyhpecw7.features.vxlan.rst
docs/pyhpecw7.rst
docs/pyhpecw7.utils.network.rst
docs/pyhpecw7.utils.rst
docs/pyhpecw7.utils.templates.cli.rst
docs/pyhpecw7.utils.templates.rst
docs/pyhpecw7.utils.validate.rst
docs/pyhpecw7.utils.xml.lib.rst
docs/pyhpecw7.utils.xml.namespaces.rst
docs/pyhpecw7.utils.xml.rst
docs/pyhpncw7.comware.rst
docs/pyhpncw7.errors.rst
docs/pyhpncw7.execkeys.rst
docs/pyhpncw7.features.cleanerase.rst
docs/pyhpncw7.features.config.rst
docs/pyhpncw7.features.errors.rst
docs/pyhpncw7.features.facts.rst
docs/pyhpncw7.features.file_copy.rst
docs/pyhpncw7.features.install_os.rst
docs/pyhpncw7.features.interface.rst
docs/pyhpncw7.features.ipinterface.rst
docs/pyhpncw7.features.irf.rst
docs/pyhpncw7.features.l2vpn.rst
docs/pyhpncw7.features.neighbor.rst
docs/pyhpncw7.features.ping.rst
docs/pyhpncw7.features.portchannel.rst
docs/pyhpncw7.features.reboot.rst
docs/pyhpncw7.features.rst
docs/pyhpncw7.features.switchport.rst
docs/pyhpncw7.features.vlan.rst
docs/pyhpncw7.features.vrrp.rst
docs/pyhpncw7.features.vxlan.rst
docs/pyhpncw7.rst
docs/pyhpncw7.utils.network.rst
docs/pyhpncw7.utils.rst
py3hpecw7.egg-info/PKG-INFO
py3hpecw7.egg-info/SOURCES.txt
py3hpecw7.egg-info/dependency_links.txt
py3hpecw7.egg-info/requires.txt
py3hpecw7.egg-info/top_level.txt
