Metadata-Version: 1.1
Name: py3hpecw7
Version: 0.1.0
Summary: Python package to simplify working with HPE Comware7 based devices
Home-page: https://github.com/vincentbernat/pyhpecw7
Author: HPE
Author-email: UNKNOWN
License: Apache2
Keywords: HPE Comware7 FlexFabric Netconf API
Platform: UNKNOWN
Classifier: Development Status :: 4 - Beta
Classifier: Intended Audience :: Developers
Classifier: Intended Audience :: System Administrators
Classifier: License :: OSI Approved :: Apache Software License
Classifier: Programming Language :: Python
Classifier: Natural Language :: English
Classifier: Operating System :: OS Independent
Classifier: Topic :: Software Development :: Libraries :: Python Modules
